LICENSE
MANIFEST.in
README.md
setup.cfg
setup.py
requirements/install.txt
requirements/tests.txt
the_big_username_blacklist/__init__.py
the_big_username_blacklist/validator.py
the_big_username_blacklist.egg-info/PKG-INFO
the_big_username_blacklist.egg-info/SOURCES.txt
the_big_username_blacklist.egg-info/dependency_links.txt
the_big_username_blacklist.egg-info/not-zip-safe
the_big_username_blacklist.egg-info/top_level.txt
the_big_username_blacklist/data/list.json