Metadata-Version: 1.1
Name: the-big-username-blacklist
Version: 1.3.0
Summary: Validate usernames against a blacklist
Home-page: https://github.com/marteinn/the-big-username-blacklist-python
Author: Martin Sandström
Author-email: martin@marteinn.se
License: MIT
Platform: UNKNOWN
Classifier: Development Status :: 5 - Production/Stable
Classifier: Intended Audience :: Developers
Classifier: Natural Language :: English
Classifier: License :: OSI Approved :: MIT License
Classifier: Programming Language :: Python
Classifier: Programming Language :: Python :: 2.7
Classifier: Programming Language :: Python :: 3.2
Classifier: Programming Language :: Python :: 3.3
Classifier: Programming Language :: Python :: 3.4
Classifier: Programming Language :: Python :: Implementation :: PyPy
